price_compare/__init__.py
price_compare/__main__.py
price_compare/mcp_server.py
price_compare/models.py
price_compare/service.py
price_compare/utils.py
price_compare/platforms/__init__.py
price_compare/platforms/base.py
price_compare/platforms/coupang.py
price_compare/platforms/etmall.py
price_compare/platforms/momo.py
price_compare/platforms/pchome.py
price_compare/platforms/rakuten.py
price_compare/platforms/shopee.py
price_compare/platforms/yahoo_auction.py
price_compare/platforms/yahoo_shopping.py
mcp_taiwan_price_compare-0.3.3.dist-info/METADATA
mcp_taiwan_price_compare-0.3.3.dist-info/WHEEL
mcp_taiwan_price_compare-0.3.3.dist-info/entry_points.txt
mcp_taiwan_price_compare-0.3.3.dist-info/licenses/LICENSE
mcp_taiwan_price_compare-0.3.3.dist-info/RECORD
