Metadata-Version: 2.4
Name: mcp-taiwan-price-compare
Version: 0.3.3
Summary: Taiwan e-commerce price comparison MCP server for momo, PChome, Coupang, ETMall, Rakuten, Yahoo
Project-URL: Homepage, https://github.com/coseto6125/mcp-taiwan-price-compare
Project-URL: Repository, https://github.com/coseto6125/mcp-taiwan-price-compare
Project-URL: Issues, https://github.com/coseto6125/mcp-taiwan-price-compare/issues
Author-email: coseto6125 <cosetoenor@gmail.com>
License-Expression: MIT
License-File: LICENSE
Keywords: ai-agent,coupang,e-commerce,etmall,mcp,momo,pchome,price-comparison,rakuten,taiwan,yahoo
Classifier: Development Status :: 3 - Alpha
Classifier: Framework :: AsyncIO
Classifier: Intended Audience :: Developers
Classifier: License :: OSI Approved :: MIT License
Classifier: Natural Language :: Chinese (Traditional)
Classifier: Operating System :: OS Independent
Classifier: Programming Language :: Python :: 3.13
Classifier: Topic :: Internet :: WWW/HTTP :: Indexing/Search
Classifier: Topic :: Office/Business
Requires-Python: >=3.13
Requires-Dist: fastmcp>=2.0.0
Requires-Dist: msgspec>=0.18.0
Requires-Dist: never-jscore>=2.5.0
Requires-Dist: never-primp>=2.1.0
Requires-Dist: regex-rs>=0.2.4
Requires-Dist: toon-format
Provides-Extra: dev
Requires-Dist: mypy>=1.0.0; extra == 'dev'
Requires-Dist: pytest-asyncio>=0.24.0; extra == 'dev'
Requires-Dist: pytest>=8.0.0; extra == 'dev'
Requires-Dist: ruff>=0.8.0; extra == 'dev'
Requires-Dist: tiktoken>=0.7.0; extra == 'dev'
